aqara_msg_push/__init__.py
aqara_msg_push/consumer.py
aqara_msg_push/tools.py
aqara_msg_push/schema/__init__.py
aqara_msg_push/schema/base.py
aqara_msg_push/schema/device_attr_msg.py
aqara_msg_push/schema/enums.py
aqara_msg_push/schema/event.py
aqara_msg_push/schema/mixin.py
aqara_msg_push/schema/toplevel.py
aqara_msg_push-1.0.2.dist-info/LICENSE
aqara_msg_push-1.0.2.dist-info/METADATA
aqara_msg_push-1.0.2.dist-info/WHEEL
aqara_msg_push-1.0.2.dist-info/top_level.txt
aqara_msg_push-1.0.2.dist-info/RECORD
