Metadata-Version: 2.1
Name: aqara-msg-push
Version: 1.0.2
Summary: Aqara Message Push SDK
Home-page: https://github.com/moff4/aqara_capi
Author: Komissarov Andrey
Author-email: Komissar.off.andrey@gmail.com
Classifier: Programming Language :: Python :: 3.10
Classifier: Operating System :: OS Independent
License-File: LICENSE
Requires-Dist: pydantic (>=1.9.0)
Requires-Dist: rocketmq-client-python (>=2.0.0)
Requires-Dist: mapping-shortcuts (>=1.1.0)
